odoo10_addon_stock_cost_method_last-10.0.1.0.0.99.dev3-py2.7-nspkg.pth
odoo/addons/stock_cost_method_last/README.rst
odoo/addons/stock_cost_method_last/__init__.py
odoo/addons/stock_cost_method_last/__manifest__.py
odoo/addons/stock_cost_method_last/i18n/stock_cost_method_last.pot
odoo/addons/stock_cost_method_last/models/__init__.py
odoo/addons/stock_cost_method_last/models/product.py
odoo/addons/stock_cost_method_last/models/stock_move.py
odoo/addons/stock_cost_method_last/static/description/icon.png
odoo/addons/stock_cost_method_last/views/product.xml
odoo10_addon_stock_cost_method_last-10.0.1.0.0.99.dev3.dist-info/METADATA
odoo10_addon_stock_cost_method_last-10.0.1.0.0.99.dev3.dist-info/RECORD
odoo10_addon_stock_cost_method_last-10.0.1.0.0.99.dev3.dist-info/WHEEL
odoo10_addon_stock_cost_method_last-10.0.1.0.0.99.dev3.dist-info/namespace_packages.txt
odoo10_addon_stock_cost_method_last-10.0.1.0.0.99.dev3.dist-info/top_level.txt
